mtap/__init__.py
mtap/__main__.py
mtap/_common.py
mtap/_config.py
mtap/_document.py
mtap/_event.py
mtap/_events_client.py
mtap/_events_client_grpc.py
mtap/_events_client_pool.py
mtap/_label_adapters.py
mtap/_label_indices.py
mtap/_labeler.py
mtap/_labels.py
mtap/_structs.py
mtap/constants.py
mtap/defaultConfig.yml
mtap/deployment.py
mtap/descriptors.py
mtap/events_server.py
mtap/metrics.py
mtap/types.py
mtap/version.py
mtap/api/__init__.py
mtap/api/v1/__init__.py
mtap/api/v1/events_pb2.py
mtap/api/v1/events_pb2.pyi
mtap/api/v1/events_pb2_grpc.py
mtap/api/v1/pipeline_pb2.py
mtap/api/v1/pipeline_pb2.pyi
mtap/api/v1/pipeline_pb2_grpc.py
mtap/api/v1/processing_pb2.py
mtap/api/v1/processing_pb2.pyi
mtap/api/v1/processing_pb2_grpc.py
mtap/examples/__init__.py
mtap/examples/exampleDeploymentConfiguration.yml
mtap/examples/examplePipelineConfiguration.yml
mtap/examples/example_pipeline.py
mtap/examples/example_processor.py
mtap/examples/example_references_processor.py
mtap/examples/print_processor_meta.py
mtap/examples/serialization/__init__.py
mtap/examples/serialization/brat_converter.py
mtap/examples/tutorial/__init__.py
mtap/examples/tutorial/hello.py
mtap/examples/tutorial/pipeline.py
mtap/examples/tutorial/serialization.py
mtap/pipeline/__init__.py
mtap/pipeline/_common.py
mtap/pipeline/_error_handling.py
mtap/pipeline/_exc.py
mtap/pipeline/_hosting.py
mtap/pipeline/_mp_config.py
mtap/pipeline/_mp_pipeline.py
mtap/pipeline/_pipeline.py
mtap/pipeline/_pipeline_components.py
mtap/pipeline/_results.py
mtap/pipeline/_sources.py
mtap/processing/__init__.py
mtap/processing/_exc.py
mtap/processing/_processing_component.py
mtap/processing/_processor.py
mtap/processing/_runners.py
mtap/processing/_service.py
mtap/processing/results.py
mtap/processors/__init__.py
mtap/processors/copy_document.py
mtap/serialization/__init__.py
mtap/serialization/_serialization.py
mtap/serialization/brat.py
mtap/serialization/event.schema.json
mtap/utilities/__init__.py
mtap-1.4.3.dist-info/LICENSE.txt
mtap-1.4.3.dist-info/METADATA
mtap-1.4.3.dist-info/WHEEL
mtap-1.4.3.dist-info/top_level.txt
mtap-1.4.3.dist-info/RECORD
