Metadata-Version: 2.1
Name: mtap
Version: 1.4.3
Summary: A framework for distributed text analysis using gRPC and microservices-based architecture.
Author-email: University of Minnesota NLP/IE Group <nlp-ie@umn.edu>, Ben Knoll <benknoll@umn.edu>
License: 
Project-URL: homepage, https://nlpie.github.io/mtap
Project-URL: documentation, https://nlpie.github.io/mtap-python-api/index.html
Project-URL: repository, https://github.com/nlpie/mtap.git
Keywords: nlp,grpc
Classifier: Development Status :: 4 - Beta
Classifier: Intended Audience :: Science/Research
Classifier: Intended Audience :: Developers
Classifier: License :: OSI Approved :: Apache Software License
Classifier: Operating System :: MacOS
Classifier: Operating System :: POSIX :: Linux
Classifier: Programming Language :: Python
Classifier: Programming Language :: Python :: 3 :: Only
Classifier: Programming Language :: Python :: 3.9
Classifier: Programming Language :: Python :: 3.10
Classifier: Programming Language :: Python :: 3.11
Classifier: Programming Language :: Python :: 3.12
Classifier: Programming Language :: Java
Classifier: Topic :: Software Development :: Libraries
Classifier: Topic :: Software Development :: Libraries :: Java Libraries
Classifier: Topic :: Software Development :: Libraries :: Python Modules
Classifier: Topic :: Text Processing :: General
Classifier: Topic :: Text Processing :: Linguistic
Requires-Python: >=3.9
License-File: LICENSE.txt
Requires-Dist: grpcio==1.66.2
Requires-Dist: grpcio-health-checking==1.66.2
Requires-Dist: grpcio-status==1.66.2
Requires-Dist: pyyaml>=6.0.0
Requires-Dist: tqdm>=4.0.0
Requires-Dist: googleapis-common-protos>=1.3.1
Requires-Dist: importlib-resources>=1.3
Provides-Extra: docs
Requires-Dist: sphinx==8.0.2; extra == "docs"
Requires-Dist: sphinx-rtd-theme==2.0.0; extra == "docs"
Provides-Extra: test
Requires-Dist: pytest==8.3.3; extra == "test"
Requires-Dist: pytest-mock==3.14.0; extra == "test"
Requires-Dist: grpcio-testing==1.66.2; extra == "test"
Requires-Dist: requests==2.32.3; extra == "test"
